odoo8_addon_l10n_de_country_states-8.0.1.0.0-py2.7-nspkg.pth
odoo_addons/l10n_de_country_states/__openerp__.py
odoo_addons/l10n_de_country_states/__init__.py
odoo_addons/l10n_de_country_states/README.rst
odoo_addons/l10n_de_country_states/models/__init__.py
odoo_addons/l10n_de_country_states/models/res_country.py
odoo_addons/l10n_de_country_states/i18n/l10n_de_country_states.pot
odoo_addons/l10n_de_country_states/i18n/de.po
odoo_addons/l10n_de_country_states/data/res_country_states.xml
odoo8_addon_l10n_de_country_states-8.0.1.0.0.dist-info/top_level.txt
odoo8_addon_l10n_de_country_states-8.0.1.0.0.dist-info/WHEEL
odoo8_addon_l10n_de_country_states-8.0.1.0.0.dist-info/RECORD
odoo8_addon_l10n_de_country_states-8.0.1.0.0.dist-info/metadata.json
odoo8_addon_l10n_de_country_states-8.0.1.0.0.dist-info/DESCRIPTION.rst
odoo8_addon_l10n_de_country_states-8.0.1.0.0.dist-info/METADATA
odoo8_addon_l10n_de_country_states-8.0.1.0.0.dist-info/namespace_packages.txt
